<!-- src/Acme/AccountBundle/Resources/config/routing.xml -->
<?xml version="1.0" encoding="UTF-8" ?>
<routes xmlns="http://symfony.com/schema/routing"
    xmlns:xsi="http://www.w3.org/2001/XMLSchema-instance"
    xsi:schemaLocation="http://symfony.com/schema/routing http://symfony.com/schema/routing/routing-1.0.xsd">

    <route id="account_register" path="/register">
        <default key="_controller">AcmeAccountBundle:Account:register</default>
    </route>

    <route id="account_create" path="/register/create">
        <default key="_controller">AcmeAccountBundle:Account:create</default>
    </route>
</routes>